FloriaGF/AsyncEvent.py
FloriaGF/Avg.py
FloriaGF/Computed.py
FloriaGF/Config.py
FloriaGF/Convert.py
FloriaGF/Core.py
FloriaGF/Exceptions.py
FloriaGF/Flag.py
FloriaGF/InstanceAttributeManager.py
FloriaGF/Loggers.py
FloriaGF/PerSecond.py
FloriaGF/PeriodicTrigger.py
FloriaGF/Stopwatch.py
FloriaGF/TimeoutScheduler.py
FloriaGF/Timer.py
FloriaGF/Utils.py
FloriaGF/Validator.py
FloriaGF/__init__.py
FloriaGF/py.typed
FloriaGF/Abc/Core.py
FloriaGF/Abc/__init__.py
FloriaGF/Abc/Graphic/Camera.py
FloriaGF/Abc/Graphic/Mesh.py
FloriaGF/Abc/Graphic/__init__.py
FloriaGF/Abc/Graphic/Batching/Batch.py
FloriaGF/Abc/Graphic/Batching/InstanceObject.py
FloriaGF/Abc/Graphic/Batching/__init__.py
FloriaGF/Abc/Graphic/Materials/Material.py
FloriaGF/Abc/Graphic/Materials/__init__.py
FloriaGF/Abc/Graphic/ShaderPrograms/BatchShaderProgram.py
FloriaGF/Abc/Graphic/ShaderPrograms/ComposeShaderProgram.py
FloriaGF/Abc/Graphic/ShaderPrograms/Scheme.py
FloriaGF/Abc/Graphic/ShaderPrograms/ShaderProgram.py
FloriaGF/Abc/Graphic/ShaderPrograms/__init__.py
FloriaGF/Abc/Graphic/Windows/Window.py
FloriaGF/Abc/Graphic/Windows/__init__.py
FloriaGF/Abc/Managers/Manager.py
FloriaGF/Abc/Managers/__init__.py
FloriaGF/Abc/Mixins/Binding.py
FloriaGF/Abc/Mixins/Copyable.py
FloriaGF/Abc/Mixins/Disposable.py
FloriaGF/Abc/Mixins/DrawRender.py
FloriaGF/Abc/Mixins/ID.py
FloriaGF/Abc/Mixins/Nameable.py
FloriaGF/Abc/Mixins/Repr.py
FloriaGF/Abc/Mixins/Serializable.py
FloriaGF/Abc/Mixins/Signaturable.py
FloriaGF/Abc/Mixins/Simulatable.py
FloriaGF/Abc/Mixins/__init__.py
FloriaGF/Assets/Asset.py
FloriaGF/Assets/Image.py
FloriaGF/Assets/Json.py
FloriaGF/Assets/Text.py
FloriaGF/Assets/__init__.py
FloriaGF/GL/Binding.py
FloriaGF/GL/Common.py
FloriaGF/GL/Convert.py
FloriaGF/GL/Draw.py
FloriaGF/GL/Logger.py
FloriaGF/GL/State.py
FloriaGF/GL/__init__.py
FloriaGF/GL/hints.py
FloriaGF/GL/Buffer/Common.py
FloriaGF/GL/Buffer/__init__.py
FloriaGF/GL/Framebuffer/Common.py
FloriaGF/GL/Framebuffer/__init__.py
FloriaGF/GL/Renderbuffer/Common.py
floriagameframeworkr7-0.0.2.dist-info/licenses/LICENSE
floriagameframeworkr7-0.0.2.dist-info/METADATA
floriagameframeworkr7-0.0.2.dist-info/WHEEL
floriagameframeworkr7-0.0.2.dist-info/top_level.txt
floriagameframeworkr7-0.0.2.dist-info/RECORD
