Metadata-Version: 2.4
Name: FloriaGameFrameworkR7
Version: 0.0.2
Summary: Экспериментальный самописный игровой фреймворк.
Author-email: FloriaProduction <FloriaProduction@yandex.ru>
License:                                  Apache License
Project-URL: Repository, https://github.com/FloriaProduction/FloriaGameFrameworkR7
Keywords: game,framework,opengl,async,2d,3d,graphics,ecs,entity-component-system
Platform: Windows
Classifier: Intended Audience :: Developers
Classifier: Topic :: Software Development :: Libraries :: Application Frameworks
Classifier: Topic :: Software Development :: Libraries :: Python Modules
Classifier: Topic :: Multimedia :: Graphics
Classifier: Topic :: Games/Entertainment
Classifier: License :: OSI Approved :: Apache Software License
Classifier: Programming Language :: Python :: 3
Classifier: Programming Language :: Python :: 3.14
Classifier: Typing :: Typed
Classifier: Operating System :: Microsoft :: Windows
Classifier: Operating System :: Microsoft :: Windows :: Windows 10
Classifier: Operating System :: Microsoft :: Windows :: Windows 11
Requires-Python: <3.15,>=3.14
License-File: LICENSE
Requires-Dist: PyOpenGL==3.1.10
Requires-Dist: glfw==2.10.0
Requires-Dist: numpy==2.3.4
Requires-Dist: pyrr==0.10.3
Requires-Dist: PILLOW==12.0.0
Requires-Dist: aiofiles==25.1.0
Provides-Extra: dev
Requires-Dist: black>=25.12.0; extra == "dev"
Dynamic: license-file
